nixtee_client/__init__.py
nixtee_client/client.py
nixtee_client-0.1.0.dist-info/METADATA
nixtee_client-0.1.0.dist-info/WHEEL
nixtee_client-0.1.0.dist-info/top_level.txt
nixtee_client-0.1.0.dist-info/RECORD
